{
  "FranchiseId": "f483ecf1-cd17-4991-854b-e52dfc957b45",
  "FranchiseName": "FB in the Groin",
  "Owner": "Scott",
  "Year": 2004,
  "SeasonSummary": {
    "Wins": 6,
    "Losses": 8,
    "Ties": 0,
    "Points": 1417,
    "Standing": 6,
    "TotalTeams": 10,
    "Champion": false,
    "SecondPlace": false,
    "MadePlayoffs": false,
    "SeasonOutcome": "Missed Playoffs"
  },
  "Performance": {
    "BestWeek": {
      "Week": 15,
      "Points": 150,
      "Opponent": "TBD",
      "OpponentPoints": 0,
      "Won": false,
      "Margin": 0
    },
    "WorstWeek": {
      "Week": 16,
      "Points": 57,
      "Opponent": "TBD",
      "OpponentPoints": 0,
      "Won": false,
      "Margin": 0
    },
    "AverageWeeklyScore": 101.5,
    "HighestWeeklyScore": 150,
    "LowestWeeklyScore": 57,
    "WeeksAsHighScorer": 1,
    "WeeksAsLowScorer": 2,
    "PointsAgainst": 0,
    "AverageMarginOfVictory": 0,
    "AverageMarginOfDefeat": 0,
    "BlowoutWins": 0,
    "HeartbreakLosses": 0
  },
  "Players": {
    "MVP": {
      "PlayerID": 4650,
      "PlayerName": "Donovan McNabb",
      "Position": "QB",
      "TotalPoints": 301.66,
      "AveragePoints": 20.110666666666666666666666667,
      "GamesStarted": 14,
      "GamesOwned": 15,
      "DraftRound": null,
      "DraftPosition": null,
      "ExpectedPoints": null,
      "PointsAboveExpected": null,
      "NflTeam": null,
      "HighlightReason": "Your highest scoring player this season"
    },
    "MostConsistent": {
      "PlayerID": 0,
      "PlayerName": "",
      "Position": "",
      "TotalPoints": 0,
      "AveragePoints": 0,
      "GamesStarted": 0,
      "GamesOwned": 0,
      "DraftRound": null,
      "DraftPosition": null,
      "ExpectedPoints": null,
      "PointsAboveExpected": null,
      "NflTeam": null,
      "HighlightReason": ""
    },
    "Breakout": {
      "PlayerID": 0,
      "PlayerName": "",
      "Position": "",
      "TotalPoints": 0,
      "AveragePoints": 0,
      "GamesStarted": 0,
      "GamesOwned": 0,
      "DraftRound": null,
      "DraftPosition": null,
      "ExpectedPoints": null,
      "PointsAboveExpected": null,
      "NflTeam": null,
      "HighlightReason": ""
    },
    "Disappointment": {
      "PlayerID": 0,
      "PlayerName": "",
      "Position": "",
      "TotalPoints": 0,
      "AveragePoints": 0,
      "GamesStarted": 0,
      "GamesOwned": 0,
      "DraftRound": null,
      "DraftPosition": null,
      "ExpectedPoints": null,
      "PointsAboveExpected": null,
      "NflTeam": null,
      "HighlightReason": ""
    },
    "BestDraftPick": {
      "PlayerID": 0,
      "PlayerName": "",
      "Position": "",
      "TotalPoints": 0,
      "AveragePoints": 0,
      "GamesStarted": 0,
      "GamesOwned": 0,
      "DraftRound": null,
      "DraftPosition": null,
      "ExpectedPoints": null,
      "PointsAboveExpected": null,
      "NflTeam": null,
      "HighlightReason": ""
    },
    "WorstDraftPick": {
      "PlayerID": 0,
      "PlayerName": "",
      "Position": "",
      "TotalPoints": 0,
      "AveragePoints": 0,
      "GamesStarted": 0,
      "GamesOwned": 0,
      "DraftRound": null,
      "DraftPosition": null,
      "ExpectedPoints": null,
      "PointsAboveExpected": null,
      "NflTeam": null,
      "HighlightReason": ""
    },
    "TopStarters": [
      {
        "PlayerID": 4650,
        "PlayerName": "Donovan McNabb",
        "Position": "QB",
        "TotalPoints": 301.66,
        "AveragePoints": 20.110666666666666666666666667,
        "GamesStarted": 14,
        "GamesOwned": 15,
        "DraftRound": null,
        "DraftPosition": null,
        "ExpectedPoints": null,
        "PointsAboveExpected": null,
        "NflTeam": null,
        "HighlightReason": "Your highest scoring player this season"
      },
      {
        "PlayerID": 3164,
        "PlayerName": "Curtis Martin",
        "Position": "RB",
        "TotalPoints": 257.0,
        "AveragePoints": 17.133333333333333333333333333,
        "GamesStarted": 10,
        "GamesOwned": 15,
        "DraftRound": null,
        "DraftPosition": null,
        "ExpectedPoints": null,
        "PointsAboveExpected": null,
        "NflTeam": null,
        "HighlightReason": "Top performer for your team"
      },
      {
        "PlayerID": 5798,
        "PlayerName": "Drew Bennett",
        "Position": "WR",
        "TotalPoints": 189.34,
        "AveragePoints": 12.622666666666666666666666667,
        "GamesStarted": 7,
        "GamesOwned": 15,
        "DraftRound": null,
        "DraftPosition": null,
        "ExpectedPoints": null,
        "PointsAboveExpected": null,
        "NflTeam": null,
        "HighlightReason": "Top performer for your team"
      },
      {
        "PlayerID": 4259,
        "PlayerName": "Fred Taylor",
        "Position": "RB",
        "TotalPoints": 176.9,
        "AveragePoints": 11.793333333333333333333333333,
        "GamesStarted": 12,
        "GamesOwned": 15,
        "DraftRound": null,
        "DraftPosition": null,
        "ExpectedPoints": null,
        "PointsAboveExpected": null,
        "NflTeam": null,
        "HighlightReason": "Top performer for your team"
      },
      {
        "PlayerID": 2354,
        "PlayerName": "Jerome Bettis",
        "Position": "RB",
        "TotalPoints": 170.1,
        "AveragePoints": 11.34,
        "GamesStarted": 1,
        "GamesOwned": 15,
        "DraftRound": null,
        "DraftPosition": null,
        "ExpectedPoints": null,
        "PointsAboveExpected": null,
        "NflTeam": null,
        "HighlightReason": "Top performer for your team"
      }
    ]
  },
  "LeagueComparisons": {
    "PointsRank": 3,
    "PointsRankSuffix": "rd",
    "PointsAboveAverage": 32.2,
    "WinsRank": 6,
    "WinsRankSuffix": "th",
    "WinPercentage": 0,
    "LeagueAverageWinPercentage": 0,
    "HighScoreWeeksRank": 0,
    "ConsistencyRank": 0,
    "StrongestPosition": "",
    "WeakestPosition": "",
    "BenchPoints": 879.84,
    "BenchPointsRank": 2,
    "BenchPointsRankSuffix": "nd",
    "BenchPointsAboveAverage": 155.034,
    "TopBenchPlayer": {
      "PlayerID": 2354,
      "PlayerName": "Jerome Bettis",
      "Position": "RB",
      "TotalPoints": 156.9,
      "AveragePoints": 0,
      "GamesStarted": 0,
      "GamesOwned": 14,
      "DraftRound": null,
      "DraftPosition": null,
      "ExpectedPoints": null,
      "PointsAboveExpected": null,
      "NflTeam": null,
      "HighlightReason": "Your best bench performer"
    },
    "TotalPlayersUsed": 16,
    "TotalPlayersUsedRank": 8,
    "TotalPlayersUsedRankSuffix": "th",
    "AvgPlayersUsedInLeague": 19.5,
    "QuarterbacksUsed": 3,
    "RunningBacksUsed": 5,
    "WideReceiversUsed": 6,
    "TightEndsUsed": 2,
    "KickersUsed": 0,
    "DefensesUsed": 0,
    "QBUsageRank": 6,
    "RBUsageRank": 7,
    "WRUsageRank": 5,
    "TEUsageRank": 5,
    "KUsageRank": 1,
    "DSTUsageRank": 1,
    "QuarterbackPoints": 459.66,
    "RunningBackPoints": 414.7,
    "WideReceiverPoints": 461.04,
    "TightEndPoints": 164.2,
    "KickerPoints": 0,
    "DefensePoints": 0,
    "QBPointsRank": 4,
    "RBPointsRank": 4,
    "WRPointsRank": 3,
    "TEPointsRank": 1,
    "KPointsRank": 1,
    "DSTPointsRank": 1,
    "AvgQBPointsInLeague": 458.386,
    "AvgRBPointsInLeague": 407.582,
    "AvgWRPointsInLeague": 410.932,
    "AvgTEPointsInLeague": 99.92,
    "AvgKPointsInLeague": 0,
    "AvgDSTPointsInLeague": 0
  },
  "FunFacts": [
    "You were in the top 3 in points scored this season!",
    "You rostered 22 different players throughout the season!",
    "Your bench was ranked #2 in scoring - great depth!",
    "You used the most different kickers - variety is the spice of life!",
    "Your bench scored 59% as many points as your starters - incredible depth!"
  ],
  "Achievements": [],
  "HeadToHeadRecords": []
}