{
  "FranchiseId": "f5908944-6efd-40eb-af54-6c53004e0e2f",
  "FranchiseName": "Mad Guys",
  "Owner": "Dave",
  "Year": 2023,
  "SeasonSummary": {
    "Wins": 8,
    "Losses": 7,
    "Ties": 0,
    "Points": 1667.08,
    "Standing": 6,
    "TotalTeams": 10,
    "Champion": false,
    "SecondPlace": false,
    "MadePlayoffs": false,
    "SeasonOutcome": "Missed Playoffs"
  },
  "Performance": {
    "BestWeek": {
      "Week": 5,
      "Points": 137.04,
      "Opponent": "TBD",
      "OpponentPoints": 0,
      "Won": false,
      "Margin": 0
    },
    "WorstWeek": {
      "Week": 4,
      "Points": 79.36,
      "Opponent": "TBD",
      "OpponentPoints": 0,
      "Won": false,
      "Margin": 0
    },
    "AverageWeeklyScore": 110.550588235294,
    "HighestWeeklyScore": 137.04,
    "LowestWeeklyScore": 79.36,
    "WeeksAsHighScorer": 3,
    "WeeksAsLowScorer": 1,
    "PointsAgainst": 0,
    "AverageMarginOfVictory": 0,
    "AverageMarginOfDefeat": 0,
    "BlowoutWins": 0,
    "HeartbreakLosses": 0
  },
  "Players": {
    "MVP": {
      "PlayerID": 29399,
      "PlayerName": "Tyreek Hill",
      "Position": "WR",
      "TotalPoints": 202.1,
      "AveragePoints": 11.888235294117647058823529412,
      "GamesStarted": 15,
      "GamesOwned": 17,
      "DraftRound": null,
      "DraftPosition": null,
      "ExpectedPoints": null,
      "PointsAboveExpected": null,
      "NflTeam": null,
      "HighlightReason": "Your highest scoring player this season"
    },
    "MostConsistent": {
      "PlayerID": 0,
      "PlayerName": "",
      "Position": "",
      "TotalPoints": 0,
      "AveragePoints": 0,
      "GamesStarted": 0,
      "GamesOwned": 0,
      "DraftRound": null,
      "DraftPosition": null,
      "ExpectedPoints": null,
      "PointsAboveExpected": null,
      "NflTeam": null,
      "HighlightReason": ""
    },
    "Breakout": {
      "PlayerID": 0,
      "PlayerName": "",
      "Position": "",
      "TotalPoints": 0,
      "AveragePoints": 0,
      "GamesStarted": 0,
      "GamesOwned": 0,
      "DraftRound": null,
      "DraftPosition": null,
      "ExpectedPoints": null,
      "PointsAboveExpected": null,
      "NflTeam": null,
      "HighlightReason": ""
    },
    "Disappointment": {
      "PlayerID": 0,
      "PlayerName": "",
      "Position": "",
      "TotalPoints": 0,
      "AveragePoints": 0,
      "GamesStarted": 0,
      "GamesOwned": 0,
      "DraftRound": null,
      "DraftPosition": null,
      "ExpectedPoints": null,
      "PointsAboveExpected": null,
      "NflTeam": null,
      "HighlightReason": ""
    },
    "BestDraftPick": {
      "PlayerID": 0,
      "PlayerName": "",
      "Position": "",
      "TotalPoints": 0,
      "AveragePoints": 0,
      "GamesStarted": 0,
      "GamesOwned": 0,
      "DraftRound": null,
      "DraftPosition": null,
      "ExpectedPoints": null,
      "PointsAboveExpected": null,
      "NflTeam": null,
      "HighlightReason": ""
    },
    "WorstDraftPick": {
      "PlayerID": 0,
      "PlayerName": "",
      "Position": "",
      "TotalPoints": 0,
      "AveragePoints": 0,
      "GamesStarted": 0,
      "GamesOwned": 0,
      "DraftRound": null,
      "DraftPosition": null,
      "ExpectedPoints": null,
      "PointsAboveExpected": null,
      "NflTeam": null,
      "HighlightReason": ""
    },
    "TopStarters": [
      {
        "PlayerID": 29399,
        "PlayerName": "Tyreek Hill",
        "Position": "WR",
        "TotalPoints": 202.1,
        "AveragePoints": 11.888235294117647058823529412,
        "GamesStarted": 15,
        "GamesOwned": 17,
        "DraftRound": null,
        "DraftPosition": null,
        "ExpectedPoints": null,
        "PointsAboveExpected": null,
        "NflTeam": null,
        "HighlightReason": "Your highest scoring player this season"
      },
      {
        "PlayerID": 25812,
        "PlayerName": "Kirk Cousins",
        "Position": "QB",
        "TotalPoints": 163.74,
        "AveragePoints": 9.631764705882352941176470588,
        "GamesStarted": 8,
        "GamesOwned": 17,
        "DraftRound": null,
        "DraftPosition": null,
        "ExpectedPoints": null,
        "PointsAboveExpected": null,
        "NflTeam": null,
        "HighlightReason": "Top performer for your team"
      },
      {
        "PlayerID": 33991,
        "PlayerName": "Breece Hall",
        "Position": "RB",
        "TotalPoints": 154.7,
        "AveragePoints": 9.1,
        "GamesStarted": 12,
        "GamesOwned": 17,
        "DraftRound": null,
        "DraftPosition": null,
        "ExpectedPoints": null,
        "PointsAboveExpected": null,
        "NflTeam": null,
        "HighlightReason": "Top performer for your team"
      },
      {
        "PlayerID": 32671,
        "PlayerName": "Joe Burrow",
        "Position": "QB",
        "TotalPoints": 142.42,
        "AveragePoints": 8.377647058823529411764705882,
        "GamesStarted": 10,
        "GamesOwned": 17,
        "DraftRound": null,
        "DraftPosition": null,
        "ExpectedPoints": null,
        "PointsAboveExpected": null,
        "NflTeam": null,
        "HighlightReason": "Top performer for your team"
      },
      {
        "PlayerID": 40042,
        "PlayerName": "Jordan Addison",
        "Position": "WR",
        "TotalPoints": 128.6,
        "AveragePoints": 7.5647058823529411764705882353,
        "GamesStarted": 14,
        "GamesOwned": 17,
        "DraftRound": null,
        "DraftPosition": null,
        "ExpectedPoints": null,
        "PointsAboveExpected": null,
        "NflTeam": null,
        "HighlightReason": "Top performer for your team"
      }
    ]
  },
  "LeagueComparisons": {
    "PointsRank": 5,
    "PointsRankSuffix": "th",
    "PointsAboveAverage": 25.432,
    "WinsRank": 4,
    "WinsRankSuffix": "th",
    "WinPercentage": 0,
    "LeagueAverageWinPercentage": 0,
    "HighScoreWeeksRank": 0,
    "ConsistencyRank": 0,
    "StrongestPosition": "",
    "WeakestPosition": "",
    "BenchPoints": 591.18,
    "BenchPointsRank": 7,
    "BenchPointsRankSuffix": "th",
    "BenchPointsAboveAverage": -66.114,
    "TopBenchPlayer": {
      "PlayerID": 27564,
      "PlayerName": "Derek Carr",
      "Position": "QB",
      "TotalPoints": 86.96,
      "AveragePoints": 0,
      "GamesStarted": 0,
      "GamesOwned": 8,
      "DraftRound": null,
      "DraftPosition": null,
      "ExpectedPoints": null,
      "PointsAboveExpected": null,
      "NflTeam": null,
      "HighlightReason": "Your best bench performer"
    },
    "TotalPlayersUsed": 21,
    "TotalPlayersUsedRank": 7,
    "TotalPlayersUsedRankSuffix": "th",
    "AvgPlayersUsedInLeague": 22.3,
    "QuarterbacksUsed": 6,
    "RunningBacksUsed": 6,
    "WideReceiversUsed": 7,
    "TightEndsUsed": 2,
    "KickersUsed": 0,
    "DefensesUsed": 0,
    "QBUsageRank": 2,
    "RBUsageRank": 5,
    "WRUsageRank": 7,
    "TEUsageRank": 7,
    "KUsageRank": 1,
    "DSTUsageRank": 1,
    "QuarterbackPoints": 371.16,
    "RunningBackPoints": 295.5,
    "WideReceiverPoints": 451.0,
    "TightEndPoints": 88.2,
    "KickerPoints": 0,
    "DefensePoints": 0,
    "QBPointsRank": 8,
    "RBPointsRank": 8,
    "WRPointsRank": 2,
    "TEPointsRank": 8,
    "KPointsRank": 1,
    "DSTPointsRank": 1,
    "AvgQBPointsInLeague": 462.806,
    "AvgRBPointsInLeague": 325.286,
    "AvgWRPointsInLeague": 396.846,
    "AvgTEPointsInLeague": 99.91,
    "AvgKPointsInLeague": 0,
    "AvgDSTPointsInLeague": 0
  },
  "FunFacts": [
    "You were in the top 5 in points scored this season!",
    "You rostered 34 different players throughout the season!",
    "You used the most different kickers - variety is the spice of life!",
    "Your bench scored 49% as many points as your starters - incredible depth!"
  ],
  "Achievements": [],
  "HeadToHeadRecords": []
}